Workbook

Sheet 指标总览
A1: 平台 | B1: 店铺/品牌 | C1: 报表类型 | D1: 时间粒度 | E1: 统计区间 | F1: 列序号 | G1: 原始列名 | H1: 基础指标名 | I1: 列角色 | J1: 是否度量 | K1: 本期首行值 | L1: 推断数据类型 | M1: 来源文件
A2: 京东 | B2: 11623441 | C2: 交易概况 | D2: 分天 | E2: 2026-09-28 ~ 2026-09-28 | F2: 1 | G2: 时间 | H2: 时间 | I2: 维度 | J2: 否 | K2: 待填充 | L2: 文本 | M2: 11623441_交易概况_包括对比时间_离线_分天下载_2026-09-28_2026-09-28.xlsx
A3: 京东 | B3: 11623441 | C3: 交易概况 | D3: 分天 | E3: 2026-09-28 ~ 2026-09-28 | F3: 2 | G3: 成交金额 | H3: 成交金额 | I3: 本期值 | J3: 是 | K3: 待填充 | L3: 小数 | M3: 11623441_交易概况_包括对比时间_离线_分天下载_2026-09-28_2026-09-28.xlsx
A4: 京东 | B4: 11623441 | C4: 交易概况 | D4: 分天 | E4: 2026-09-28 ~ 2026-09-28 | F4: 3 | G4: 成交金额-对比日 | H4: 成交金额 | I4: 对比日 | J4: 是 | K4: 待填充 | L4: 小数 | M4: 11623441_交易概况_包括对比时间_离线_分天下载_2026-09-28_2026-09-28.xlsx
A5: 京东 | B5: 11623441 | C5: 交易概况 | D5: 分天 | E5: 2026-09-28 ~ 2026-09-28 | F5: 4 | G5: 成交金额-较对比日 | H5: 成交金额 | I5: 较对比日 | J5: 是 | K5: 待填充 | L5: 小数 | M5: 11623441_交易概况_包括对比时间_离线_分天下载_2026-09-28_2026-09-28.xlsx
A6: 京东 | B6: 11623441 | C6: 交易概况 | D6: 分天 | E6: 2026-09-28 ~ 2026-09-28 | F6: 5 | G6: 成交商品件数 | H6: 成交商品件数 | I6: 本期值 | J6: 是 | K6: 待填充 | L6: 整数 | M6: 11623441_交易概况_包括对比时间_离线_分天下载_2026-09-28_2026-09-28.xlsx
A7: 京东 | B7: 11623441 | C7: 交易概况 | D7: 分天 | E7: 2026-09-28 ~ 2026-09-28 | F7: 6 | G7: 成交商品件数-对比日 | H7: 成交商品件数 | I7: 对比日 | J7: 是 | K7: 待填充 | L7: 整数 | M7: 11623441_交易概况_包括对比时间_离线_分天下载_2026-09-28_2026-09-28.xlsx
A8: 京东 | B8: 11623441 | C8: 交易概况 | D8: 分天 | E8: 2026-09-28 ~ 2026-09-28 | F8: 7 | G8: 成交商品件数-较对比日 | H8: 成交商品件数 | I8: 较对比日 | J8: 是 | K8: 待填充 | L8: 整数 | M8: 11623441_交易概况_包括对比时间_离线_分天下载_2026-09-28_2026-09-28.xlsx
A9: 京东 | B9: 11623441 | C9: 交易概况 | D9: 分天 | E9: 2026-09-28 ~ 2026-09-28 | F9: 8 | G9: 成交客户数 | H9: 成交客户数 | I9: 本期值 | J9: 是 | K9: 待填充 | L9: 整数 | M9: 11623441_交易概况_包括对比时间_离线_分天下载_2026-09-28_2026-09-28.xlsx
A10: 京东 | B10: 11623441 | C10: 交易概况 | D10: 分天 | E10: 2026-09-28 ~ 2026-09-28 | F10: 9 | G10: 成交客户数-对比日 | H10: 成交客户数 | I10: 对比日 | J10: 是 | K10: 待填充 | L10: 整数 | M10: 11623441_交易概况_包括对比时间_离线_分天下载_2026-09-28_2026-09-28.xlsx
A11: 京东 | B11: 11623441 | C11: 交易概况 | D11: 分天 | E11: 2026-09-28 ~ 2026-09-28 | F11: 10 | G11: 成交客户数-较对比日 | H11: 成交客户数 | I11: 较对比日 | J11: 是 | K11: 待填充 | L11: 整数 | M11: 11623441_交易概况_包括对比时间_离线_分天下载_2026-09-28_2026-09-28.xlsx
A12: 京东 | B12: 11623441 | C12: 交易概况 | D12: 分天 | E12: 2026-09-28 ~ 2026-09-28 | F12: 11 | G12: 成交单量 | H12: 成交单量 | I12: 本期值 | J12: 是 | K12: 待填充 | L12: 整数 | M12: 11623441_交易概况_包括对比时间_离线_分天下载_2026-09-28_2026-09-28.xlsx
A13: 京东 | B13: 11623441 | C13: 交易概况 | D13: 分天 | E13: 2026-09-28 ~ 2026-09-28 | F13: 12 | G13: 成交单量-对比日 | H13: 成交单量 | I13: 对比日 | J13: 是 | K13: 待填充 | L13: 整数 | M13: 11623441_交易概况_包括对比时间_离线_分天下载_2026-09-28_2026-09-28.xlsx
... A312: 京东 | B312: 11623441 | C312: 商品明细 | D312: 汇总 | E312: 2026-09-29 00:00:00 ~ 2026-09-29 10:00:21 | F312: 27 | G312: 取消订单单量 | H312: 取消订单单量 | I312: 本期值 | J312: 是 | K312: 待填充 | L312: 整数 | M312: 11623441_商品明细_实时_汇总下载_2026-09-29_00_00_00_2026-09-29_10_00_21.xlsx
A313: 京东 | B313: 小巴依-奔羊羊 | C313: 报表中心_计划_30天_点击_不含赠品_成交订单 | D313: 未标注 | E313: 2026-09-23 ~ 2026-09-29 | F313: 1 | G313: 点击时间 | H313: 点击时间 | I313: 本期值 | J313: 是 | K313: 待填充 | L313: 文本 | M313: 小巴依-奔羊羊_报表中心_计划_30天_点击_不含赠品_成交订单_20260923_20260929.csv
A314: 京东 | B314: 小巴依-奔羊羊 | C314: 报表中心_计划_30天_点击_不含赠品_成交订单 | D314: 未标注 | E314: 2026-09-23 ~ 2026-09-29 | F314: 2 | G314: 计划ID | H314: 计划ID | I314: 本期值 | J314: 是 | K314: 待填充 | L314: 文本 | M314: 小巴依-奔羊羊_报表中心_计划_30天_点击_不含赠品_成交订单_20260923_20260929.csv
A315: 京东 | B315: 小巴依-奔羊羊 | C315: 报表中心_计划_30天_点击_不含赠品_成交订单 | D315: 未标注 | E315: 2026-09-23 ~ 2026-09-29 | F315: 3 | G315: 推广计划 | H315: 推广计划 | I315: 本期值 | J315: 是 | K315: 待填充 | L315: 文本 | M315: 小巴依-奔羊羊_报表中心_计划_30天_点击_不含赠品_成交订单_20260923_20260929.csv
A316: 京东 | B316: 小巴依-奔羊羊 | C316: 报表中心_计划_30天_点击_不含赠品_成交订单 | D316: 未标注 | E316: 2026-09-23 ~ 2026-09-29 | F316: 4 | G316: 展现数 | H316: 展现数 | I316: 本期值 | J316: 是 | K316: 待填充 | L316: 整数 | M316: 小巴依-奔羊羊_报表中心_计划_30天_点击_不含赠品_成交订单_20260923_20260929.csv
A317: 京东 | B317: 小巴依-奔羊羊 | C317: 报表中心_计划_30天_点击_不含赠品_成交订单 | D317: 未标注 | E317: 2026-09-23 ~ 2026-09-29 | F317: 5 | G317: 点击数 | H317: 点击数 | I317: 本期值 | J317: 是 | K317: 待填充 | L317: 整数 | M317: 小巴依-奔羊羊_报表中心_计划_30天_点击_不含赠品_成交订单_20260923_20260929.csv
A318: 京东 | B318: 小巴依-奔羊羊 | C318: 报表中心_计划_30天_点击_不含赠品_成交订单 | D318: 未标注 | E318: 2026-09-23 ~ 2026-09-29 | F318: 6 | G318: 点击率(%) | H318: 点击率(%) | I318: 本期值 | J318: 是 | K318: 待填充 | L318: 文本 | M318: 小巴依-奔羊羊_报表中心_计划_30天_点击_不含赠品_成交订单_20260923_20260929.csv
A319: 京东 | B319: 小巴依-奔羊羊 | C319: 报表中心_计划_30天_点击_不含赠品_成交订单 | D319: 未标注 | E319: 2026-09-23 ~ 2026-09-29 | F319: 7 | G319: 花费 | H319: 花费 | I319: 本期值 | J319: 是 | K319: 待填充 | L319: 文本 | M319: 小巴依-奔羊羊_报表中心_计划_30天_点击_不含赠品_成交订单_20260923_20260929.csv
A320: 京东 | B320: 小巴依-奔羊羊 | C320: 报表中心_计划_30天_点击_不含赠品_成交订单 | D320: 未标注 | E320: 2026-09-23 ~ 2026-09-29 | F320: 8 | G320: 千次展现成本 | H320: 千次展现成本 | I320: 本期值 | J320: 是 | K320: 待填充 | L320: 小数 | M320: 小巴依-奔羊羊_报表中心_计划_30天_点击_不含赠品_成交订单_20260923_20260929.csv
A321: 京东 | B321: 小巴依-奔羊羊 | C321: 报表中心_计划_30天_点击_不含赠品_成交订单 | D321: 未标注 | E321: 2026-09-23 ~ 2026-09-29 | F321: 9 | G321: 平均点击成本 | H321: 平均点击成本 | I321: 本期值 | J321: 是 | K321: 待填充 | L321: 小数 | M321: 小巴依-奔羊羊_报表中心_计划_30天_点击_不含赠品_成交订单_20260923_20260929.csv
A322: 京东 | B322: 小巴依-奔羊羊 | C322: 报表中心_计划_30天_点击_不含赠品_成交订单 | D322: 未标注 | E322: 2026-09-23 ~ 2026-09-29 | F322: 10 | G322: 带券展现 | H322: 带券展现 | I322: 本期值 | J322: 是 | K322: 待填充 | L322: 文本 | M322: 小巴依-奔羊羊_报表中心_计划_30天_点击_不含赠品_成交订单_20260923_20260929.csv
A323: 京东 | B323: 小巴依-奔羊羊 | C323: 报表中心_计划_30天_点击_不含赠品_成交订单 | D323: 未标注 | E323: 2026-09-23 ~ 2026-09-29 | F323: 11 | G323: 带券点击 | H323: 带券点击 | I323: 本期值 | J323: 是 | K323: 待填充 | L323: 文本 | M323: 小巴依-奔羊羊_报表中心_计划_30天_点击_不含赠品_成交订单_20260923_20260929.csv
A324: 京东 | B324: 小巴依-奔羊羊 | C324: 报表中心_计划_30天_点击_不含赠品_成交订单 | D324: 未标注 | E324: 2026-09-23 ~ 2026-09-29 | F324: 12 | G324: 直接订单行 | H324: 直接订单行 | I324: 本期值 | J324: 是 | K324: 待填充 | L324: 整数 | M324: 小巴依-奔羊羊_报表中心_计划_30天_点击_不含赠品_成交订单_20260923_20260929.csv
... A392: 京东 | B392: 未标注 | C392: 用户洞察-数据概览 | D392: 未标注 | E392: 2026-09-28 ~ 2026-09-28 | F392: 27 | G392: 成交-复购率同比 | H392: 成交-复购率 | I392: 同比 | J392: 是 | K392: 待填充 | L392: 小数 | M392: 用户洞察-数据概览-2026.09.28-同比.xlsx

Sheet 商品渠道
A1: 七(下)、单品-各渠道贡献：在 D2 下拉选择 SPU，下方表格与饼图随之更新
A2: 选择商品
A4: 渠道 | B4: 销售额 | C4: 销售件数 | D4: 下单人数 | E4: 占该品比
B5: =SUMIFS(明细数据!$L:$L,明细数据!$C:$C,"",明细数据!$K:$K,"本期值",明细数据!$H:$H,$D$2,明细数据!$F:$F,$A5,明细数据!$J:$J,"成交金额") -> 0 | C5: =SUMIFS(明细数据!$L:$L,明细数据!$C:$C,"",明细数据!$K:$K,"本期值",明细数据!$H:$H,$D$2,明细数据!$F:$F,$A5,明细数据!$J:$J,"成交商品件数") -> 0 | D5: =SUMIFS(明细数据!$L:$L,明细数据!$C:$C,"",明细数据!$K:$K,"本期值",明细数据!$H:$H,$D$2,明细数据!$F:$F,$A5,明细数据!$J:$J,"成交客户数") -> 0 | E5: =IFERROR($B5/SUM($B$5:$B$14),NA()) -> #N/A
B6: =SUMIFS(明细数据!$L:$L,明细数据!$C:$C,"",明细数据!$K:$K,"本期值",明细数据!$H:$H,$D$2,明细数据!$F:$F,$A6,明细数据!$J:$J,"成交金额") -> 0 | C6: =SUMIFS(明细数据!$L:$L,明细数据!$C:$C,"",明细数据!$K:$K,"本期值",明细数据!$H:$H,$D$2,明细数据!$F:$F,$A6,明细数据!$J:$J,"成交商品件数") -> 0 | D6: =SUMIFS(明细数据!$L:$L,明细数据!$C:$C,"",明细数据!$K:$K,"本期值",明细数据!$H:$H,$D$2,明细数据!$F:$F,$A6,明细数据!$J:$J,"成交客户数") -> 0 | E6: =IFERROR($B6/SUM($B$5:$B$14),NA()) -> #N/A
B7: =SUMIFS(明细数据!$L:$L,明细数据!$C:$C,"",明细数据!$K:$K,"本期值",明细数据!$H:$H,$D$2,明细数据!$F:$F,$A7,明细数据!$J:$J,"成交金额") -> 0 | C7: =SUMIFS(明细数据!$L:$L,明细数据!$C:$C,"",明细数据!$K:$K,"本期值",明细数据!$H:$H,$D$2,明细数据!$F:$F,$A7,明细数据!$J:$J,"成交商品件数") -> 0 | D7: =SUMIFS(明细数据!$L:$L,明细数据!$C:$C,"",明细数据!$K:$K,"本期值",明细数据!$H:$H,$D$2,明细数据!$F:$F,$A7,明细数据!$J:$J,"成交客户数") -> 0 | E7: =IFERROR($B7/SUM($B$5:$B$14),NA()) -> #N/A
B8: =SUMIFS(明细数据!$L:$L,明细数据!$C:$C,"",明细数据!$K:$K,"本期值",明细数据!$H:$H,$D$2,明细数据!$F:$F,$A8,明细数据!$J:$J,"成交金额") -> 0 | C8: =SUMIFS(明细数据!$L:$L,明细数据!$C:$C,"",明细数据!$K:$K,"本期值",明细数据!$H:$H,$D$2,明细数据!$F:$F,$A8,明细数据!$J:$J,"成交商品件数") -> 0 | D8: =SUMIFS(明细数据!$L:$L,明细数据!$C:$C,"",明细数据!$K:$K,"本期值",明细数据!$H:$H,$D$2,明细数据!$F:$F,$A8,明细数据!$J:$J,"成交客户数") -> 0 | E8: =IFERROR($B8/SUM($B$5:$B$14),NA()) -> #N/A
B9: =SUMIFS(明细数据!$L:$L,明细数据!$C:$C,"",明细数据!$K:$K,"本期值",明细数据!$H:$H,$D$2,明细数据!$F:$F,$A9,明细数据!$J:$J,"成交金额") -> 0 | C9: =SUMIFS(明细数据!$L:$L,明细数据!$C:$C,"",明细数据!$K:$K,"本期值",明细数据!$H:$H,$D$2,明细数据!$F:$F,$A9,明细数据!$J:$J,"成交商品件数") -> 0 | D9: =SUMIFS(明细数据!$L:$L,明细数据!$C:$C,"",明细数据!$K:$K,"本期值",明细数据!$H:$H,$D$2,明细数据!$F:$F,$A9,明细数据!$J:$J,"成交客户数") -> 0 | E9: =IFERROR($B9/SUM($B$5:$B$14),NA()) -> #N/A
B10: =SUMIFS(明细数据!$L:$L,明细数据!$C:$C,"",明细数据!$K:$K,"本期值",明细数据!$H:$H,$D$2,明细数据!$F:$F,$A10,明细数据!$J:$J,"成交金额") -> 0 | C10: =SUMIFS(明细数据!$L:$L,明细数据!$C:$C,"",明细数据!$K:$K,"本期值",明细数据!$H:$H,$D$2,明细数据!$F:$F,$A10,明细数据!$J:$J,"成交商品件数") -> 0 | D10: =SUMIFS(明细数据!$L:$L,明细数据!$C:$C,"",明细数据!$K:$K,"本期值",明细数据!$H:$H,$D$2,明细数据!$F:$F,$A10,明细数据!$J:$J,"成交客户数") -> 0 | E10: =IFERROR($B10/SUM($B$5:$B$14),NA()) -> #N/A
B11: =SUMIFS(明细数据!$L:$L,明细数据!$C:$C,"",明细数据!$K:$K,"本期值",明细数据!$H:$H,$D$2,明细数据!$F:$F,$A11,明细数据!$J:$J,"成交金额") -> 0 | C11: =SUMIFS(明细数据!$L:$L,明细数据!$C:$C,"",明细数据!$K:$K,"本期值",明细数据!$H:$H,$D$2,明细数据!$F:$F,$A11,明细数据!$J:$J,"成交商品件数") -> 0 | D11: =SUMIFS(明细数据!$L:$L,明细数据!$C:$C,"",明细数据!$K:$K,"本期值",明细数据!$H:$H,$D$2,明细数据!$F:$F,$A11,明细数据!$J:$J,"成交客户数") -> 0 | E11: =IFERROR($B11/SUM($B$5:$B$14),NA()) -> #N/A
B12: =SUMIFS(明细数据!$L:$L,明细数据!$C:$C,"",明细数据!$K:$K,"本期值",明细数据!$H:$H,$D$2,明细数据!$F:$F,$A12,明细数据!$J:$J,"成交金额") -> 0 | C12: =SUMIFS(明细数据!$L:$L,明细数据!$C:$C,"",明细数据!$K:$K,"本期值",明细数据!$H:$H,$D$2,明细数据!$F:$F,$A12,明细数据!$J:$J,"成交商品件数") -> 0 | D12: =SUMIFS(明细数据!$L:$L,明细数据!$C:$C,"",明细数据!$K:$K,"本期值",明细数据!$H:$H,$D$2,明细数据!$F:$F,$A12,明细数据!$J:$J,"成交客户数") -> 0 | E12: =IFERROR($B12/SUM($B$5:$B$14),NA()) -> #N/A
B13: =SUMIFS(明细数据!$L:$L,明细数据!$C:$C,"",明细数据!$K:$K,"本期值",明细数据!$H:$H,$D$2,明细数据!$F:$F,$A13,明细数据!$J:$J,"成交金额") -> 0 | C13: =SUMIFS(明细数据!$L:$L,明细数据!$C:$C,"",明细数据!$K:$K,"本期值",明细数据!$H:$H,$D$2,明细数据!$F:$F,$A13,明细数据!$J:$J,"成交商品件数") -> 0 | D13: =SUMIFS(明细数据!$L:$L,明细数据!$C:$C,"",明细数据!$K:$K,"本期值",明细数据!$H:$H,$D$2,明细数据!$F:$F,$A13,明细数据!$J:$J,"成交客户数") -> 0 | E13: =IFERROR($B13/SUM($B$5:$B$14),NA()) -> #N/A
B14: =SUMIFS(明细数据!$L:$L,明细数据!$C:$C,"",明细数据!$K:$K,"本期值",明细数据!$H:$H,$D$2,明细数据!$F:$F,$A14,明细数据!$J:$J,"成交金额") -> 0 | C14: =SUMIFS(明细数据!$L:$L,明细数据!$C:$C,"",明细数据!$K:$K,"本期值",明细数据!$H:$H,$D$2,明细数据!$F:$F,$A14,明细数据!$J:$J,"成交商品件数") -> 0 | D14: =SUMIFS(明细数据!$L:$L,明细数据!$C:$C,"",明细数据!$K:$K,"本期值",明细数据!$H:$H,$D$2,明细数据!$F:$F,$A14,明细数据!$J:$J,"成交客户数") -> 0 | E14: =IFERROR($B14/SUM($B$5:$B$14),NA()) -> #N/A
A16: 说明：需导入「商品×渠道」交叉明细后本表才有数；未导入前为 0，属预期。

Sheet 看板
A1: 经营看板
A2: 数据来源：明细数据（SUMIFS 活公式）+ 目标预算（可编辑）
J4: 六、预算使用率与全月使用进度（表格）
J5: 指标 | K5: 数值 | L5: 口径说明
J6: 当月广告花费 | K6: =目标预算!$B$12 -> 0 | L6: 推广报表花费合计
J7: 当月销售额 | K7: =目标预算!$B$14 -> 0 | L7: 成交金额合计（费比分母）
A8: 商品/渠道明细见「图表数据」T15 起 与「商品渠道」sheet | J8: 月度广告预算 | K8: =目标预算!$B$15 -> #N/A | L8: 取自本表 H5
J9: 当前使用率 | K9: =目标预算!$B$16 -> #N/A | L9: 已花费 / 预算
J10: 时间进度 | K10: =目标预算!$B$17 -> 0.066666667 | L10: 已过天数 / 当月总天数
J11: 全月使用进度 | K11: =目标预算!$B$18 -> #N/A | L11: 使用率 - 时间进度；正数=花钱快于走日历
J12: 实际ROI | K12: =目标预算!$B$19 -> #N/A | L12: 广告成交额 / 花费
J13: ROI达成 | K13: =目标预算!$B$21 -> #N/A | L13: 实际ROI / ROI目标
J14: 花费比例(费比) | K14: =目标预算!$B$22 -> #N/A | L14: 花费 / 销售额
J15: 费比上限 | K15: =目标预算!$B$23 -> #N/A | L15: 取自本表 H7
J16: 预算预警 | K16: =目标预算!$B$24 -> #N/A | L16: 使用率对比时间进度的阈值判断
V18: 费比 | W18: =IFERROR(图表数据!W11,"-") -> -
V19: 费比上限 | W19: =目标预算!H7 -> #N/A

Sheet 图表数据
A1: 本表全为公式，挂在「明细数据」+「目标预算」上；数据更新后图表自动重算，无需重跑脚本
A3: 渠道 | B3: 销售额 | C3: 占比 | D3: 排名 | F3: 日 | G3: 本期销售额 | H3: 上期销售额 | I3: 同比% | J3: 环比% | K3: 去年同期 | T3: 四、目标达成率
B4: =SUMIFS(明细数据!$L:$L,明细数据!$C:$C,"流量来源_流量结构分析_场域来源",明细数据!$J:$J,"引入成交金额",明细数据!$K:$K,"本期值",明细数据!$F:$F,$A4) -> 0 | C4: =IFERROR($B4/SUM($B$4:$B$13),NA()) -> #N/A | D4: =IF($B4<=0,"-",RANK($B4,$B$4:$B$13)) -> - | F4: 46282 | G4: =SUMIFS(明细数据!$L:$L,明细数据!$C:$C,"交易概况",明细数据!$J:$J,"成交金额",明细数据!$K:$K,"本期值",明细数据!$E:$E,">="&$M4,明细数据!$E:$E,"<="&$N4) -> 0 | H4: =SUMIFS(明细数据!$L:$L,明细数据!$C:$C,"交易概况",明细数据!$J:$J,"成交金额",明细数据!$K:$K,"本期值",明细数据!$E:$E,">="&$O4,明细数据!$E:$E,"<="&$P4) -> 0 | I4: =IFERROR(($G4-$K4)/$K4,NA()) -> #N/A | J4: =IFERROR(($G4-$H4)/$H4,NA()) -> #N/A | K4: =SUMIFS(明细数据!$L:$L,明细数据!$C:$C,"交易概况",明细数据!$J:$J,"成交金额",明细数据!$K:$K,"本期值",明细数据!$E:$E,">="&$Q4,明细数据!$E:$E,"<="&$R4) -> 0 | M4: 46282 | N4: 46282 | O4: 46281 | P4: 46281 | Q4: 45917 | R4: 45917 | T4: 期间 | U4: 目标 | V4: 实际 | W4: 达成率
B5: =SUMIFS(明细数据!$L:$L,明细数据!$C:$C,"流量来源_流量结构分析_场域来源",明细数据!$J:$J,"引入成交金额",明细数据!$K:$K,"本期值",明细数据!$F:$F,$A5) -> 0 | C5: =IFERROR($B5/SUM($B$4:$B$13),NA()) -> #N/A | D5: =IF($B5<=0,"-",RANK($B5,$B$4:$B$13)) -> - | F5: 46283 | G5: =SUMIFS(明细数据!$L:$L,明细数据!$C:$C,"交易概况",明细数据!$J:$J,"成交金额",明细数据!$K:$K,"本期值",明细数据!$E:$E,">="&$M5,明细数据!$E:$E,"<="&$N5) -> 0 | H5: =SUMIFS(明细数据!$L:$L,明细数据!$C:$C,"交易概况",明细数据!$J:$J,"成交金额",明细数据!$K:$K,"本期值",明细数据!$E:$E,">="&$O5,明细数据!$E:$E,"<="&$P5) -> 0 | I5: =IFERROR(($G5-$K5)/$K5,NA()) -> #N/A | J5: =IFERROR(($G5-$H5)/$H5,NA()) -> #N/A | K5: =SUMIFS(明细数据!$L:$L,明细数据!$C:$C,"交易概况",明细数据!$J:$J,"成交金额",明细数据!$K:$K,"本期值",明细数据!$E:$E,">="&$Q5,明细数据!$E:$E,"<="&$R5) -> 0 | M5: 46283 | N5: 46283 | O5: 46282 | P5: 46282 | Q5: 45918 | R5: 45918 | T5: 本月 | U5: =目标预算!$H$3 -> #N/A | V5: =SUMIFS(明细数据!$L:$L,明细数据!$C:$C,"交易概况",明细数据!$J:$J,"成交金额",明细数据!$K:$K,"本期值",明细数据!$E:$E,">="&目标预算!$H$2,明细数据!$E:$E,"<="&目标预算!$H$2+32-DAY(目标预算!$H$2)) -> 0 | W5: =IFERROR($V5/$U5,NA()) -> #N/A
B6: =SUMIFS(明细数据!$L:$L,明细数据!$C:$C,"流量来源_流量结构分析_场域来源",明细数据!$J:$J,"引入成交金额",明细数据!$K:$K,"本期值",明细数据!$F:$F,$A6) -> 0 | C6: =IFERROR($B6/SUM($B$4:$B$13),NA()) -> #N/A | D6: =IF($B6<=0,"-",RANK($B6,$B$4:$B$13)) -> - | F6: 46284 | G6: =SUMIFS(明细数据!$L:$L,明细数据!$C:$C,"交易概况",明细数据!$J:$J,"成交金额",明细数据!$K:$K,"本期值",明细数据!$E:$E,">="&$M6,明细数据!$E:$E,"<="&$N6) -> 0 | H6: =SUMIFS(明细数据!$L:$L,明细数据!$C:$C,"交易概况",明细数据!$J:$J,"成交金额",明细数据!$K:$K,"本期值",明细数据!$E:$E,">="&$O6,明细数据!$E:$E,"<="&$P6) -> 0 | I6: =IFERROR(($G6-$K6)/$K6,NA()) -> #N/A | J6: =IFERROR(($G6-$H6)/$H6,NA()) -> #N/A | K6: =SUMIFS(明细数据!$L:$L,明细数据!$C:$C,"交易概况",明细数据!$J:$J,"成交金额",明细数据!$K:$K,"本期值",明细数据!$E:$E,">="&$Q6,明细数据!$E:$E,"<="&$R6) -> 0 | M6: 46284 | N6: 46284 | O6: 46283 | P6: 46283 | Q6: 45919 | R6: 45919 | T6: 本年 | U6: =目标预算!$H$4 -> 0 | V6: =SUMIFS(明细数据!$L:$L,明细数据!$C:$C,"交易概况",明细数据!$J:$J,"成交金额",明细数据!$K:$K,"本期值",明细数据!$E:$E,">="&DATE(YEAR(目标预算!$H$2),1,1),明细数据!$E:$E,"<="&目标预算!$H$2+32-DAY(目标预算!$H$2)) -> 0 | W6: =IFERROR($V6/$U6,NA()) -> #N/A
B7: =SUMIFS(明细数据!$L:$L,明细数据!$C:$C,"流量来源_流量结构分析_场域来源",明细数据!$J:$J,"引入成交金额",明细数据!$K:$K,"本期值",明细数据!$F:$F,$A7) -> 0 | C7: =IFERROR($B7/SUM($B$4:$B$13),NA()) -> #N/A | D7: =IF($B7<=0,"-",RANK($B7,$B$4:$B$13)) -> - | F7: 46285 | G7: =SUMIFS(明细数据!$L:$L,明细数据!$C:$C,"交易概况",明细数据!$J:$J,"成交金额",明细数据!$K:$K,"本期值",明细数据!$E:$E,">="&$M7,明细数据!$E:$E,"<="&$N7) -> 0 | H7: =SUMIFS(明细数据!$L:$L,明细数据!$C:$C,"交易概况",明细数据!$J:$J,"成交金额",明细数据!$K:$K,"本期值",明细数据!$E:$E,">="&$O7,明细数据!$E:$E,"<="&$P7) -> 0 | I7: =IFERROR(($G7-$K7)/$K7,NA()) -> #N/A | J7: =IFERROR(($G7-$H7)/$H7,NA()) -> #N/A | K7: =SUMIFS(明细数据!$L:$L,明细数据!$C:$C,"交易概况",明细数据!$J:$J,"成交金额",明细数据!$K:$K,"本期值",明细数据!$E:$E,">="&$Q7,明细数据!$E:$E,"<="&$R7) -> 0 | M7: 46285 | N7: 46285 | O7: 46284 | P7: 46284 | Q7: 45920 | R7: 45920
B8: =SUMIFS(明细数据!$L:$L,明细数据!$C:$C,"流量来源_流量结构分析_场域来源",明细数据!$J:$J,"引入成交金额",明细数据!$K:$K,"本期值",明细数据!$F:$F,$A8) -> 0 | C8: =IFERROR($B8/SUM($B$4:$B$13),NA()) -> #N/A | D8: =IF($B8<=0,"-",RANK($B8,$B$4:$B$13)) -> - | F8: 46286 | G8: =SUMIFS(明细数据!$L:$L,明细数据!$C:$C,"交易概况",明细数据!$J:$J,"成交金额",明细数据!$K:$K,"本期值",明细数据!$E:$E,">="&$M8,明细数据!$E:$E,"<="&$N8) -> 0 | H8: =SUMIFS(明细数据!$L:$L,明细数据!$C:$C,"交易概况",明细数据!$J:$J,"成交金额",明细数据!$K:$K,"本期值",明细数据!$E:$E,">="&$O8,明细数据!$E:$E,"<="&$P8) -> 0 | I8: =IFERROR(($G8-$K8)/$K8,NA()) -> #N/A | J8: =IFERROR(($G8-$H8)/$H8,NA()) -> #N/A | K8: =SUMIFS(明细数据!$L:$L,明细数据!$C:$C,"交易概况",明细数据!$J:$J,"成交金额",明细数据!$K:$K,"本期值",明细数据!$E:$E,">="&$Q8,明细数据!$E:$E,"<="&$R8) -> 0 | M8: 46286 | N8: 46286 | O8: 46285 | P8: 46285 | Q8: 45921 | R8: 45921
B9: =SUMIFS(明细数据!$L:$L,明细数据!$C:$C,"流量来源_流量结构分析_场域来源",明细数据!$J:$J,"引入成交金额",明细数据!$K:$K,"本期值",明细数据!$F:$F,$A9) -> 0 | C9: =IFERROR($B9/SUM($B$4:$B$13),NA()) -> #N/A | D9: =IF($B9<=0,"-",RANK($B9,$B$4:$B$13)) -> - | F9: 46287 | G9: =SUMIFS(明细数据!$L:$L,明细数据!$C:$C,"交易概况",明细数据!$J:$J,"成交金额",明细数据!$K:$K,"本期值",明细数据!$E:$E,">="&$M9,明细数据!$E:$E,"<="&$N9) -> 0 | H9: =SUMIFS(明细数据!$L:$L,明细数据!$C:$C,"交易概况",明细数据!$J:$J,"成交金额",明细数据!$K:$K,"本期值",明细数据!$E:$E,">="&$O9,明细数据!$E:$E,"<="&$P9) -> 0 | I9: =IFERROR(($G9-$K9)/$K9,NA()) -> #N/A | J9: =IFERROR(($G9-$H9)/$H9,NA()) -> #N/A | K9: =SUMIFS(明细数据!$L:$L,明细数据!$C:$C,"交易概况",明细数据!$J:$J,"成交金额",明细数据!$K:$K,"本期值",明细数据!$E:$E,">="&$Q9,明细数据!$E:$E,"<="&$R9) -> 0 | M9: 46287 | N9: 46287 | O9: 46286 | P9: 46286 | Q9: 45922 | R9: 45922 | T9: 五、广告ROI与费比
B10: =SUMIFS(明细数据!$L:$L,明细数据!$C:$C,"流量来源_流量结构分析_场域来源",明细数据!$J:$J,"引入成交金额",明细数据!$K:$K,"本期值",明细数据!$F:$F,$A10) -> 0 | C10: =IFERROR($B10/SUM($B$4:$B$13),NA()) -> #N/A | D10: =IF($B10<=0,"-",RANK($B10,$B$4:$B$13)) -> - | F10: 46288 | G10: =SUMIFS(明细数据!$L:$L,明细数据!$C:$C,"交易概况",明细数据!$J:$J,"成交金额",明细数据!$K:$K,"本期值",明细数据!$E:$E,">="&$M10,明细数据!$E:$E,"<="&$N10) -> 0 | H10: =SUMIFS(明细数据!$L:$L,明细数据!$C:$C,"交易概况",明细数据!$J:$J,"成交金额",明细数据!$K:$K,"本期值",明细数据!$E:$E,">="&$O10,明细数据!$E:$E,"<="&$P10) -> 0 | I10: =IFERROR(($G10-$K10)/$K10,NA()) -> #N/A | J10: =IFERROR(($G10-$H10)/$H10,NA()) -> #N/A | K10: =SUMIFS(明细数据!$L:$L,明细数据!$C:$C,"交易概况",明细数据!$J:$J,"成交金额",明细数据!$K:$K,"本期值",明细数据!$E:$E,">="&$Q10,明细数据!$E:$E,"<="&$R10) -> 0 | M10: 46288 | N10: 46288 | O10: 46287 | P10: 46287 | Q10: 45923 | R10: 45923 | T10: 期间 | U10: ROI目标 | V10: 实际ROI | W10: 费比
B11: =SUMIFS(明细数据!$L:$L,明细数据!$C:$C,"流量来源_流量结构分析_场域来源",明细数据!$J:$J,"引入成交金额",明细数据!$K:$K,"本期值",明细数据!$F:$F,$A11) -> 0 | C11: =IFERROR($B11/SUM($B$4:$B$13),NA()) -> #N/A | D11: =IF($B11<=0,"-",RANK($B11,$B$4:$B$13)) -> - | F11: 46289 | G11: =SUMIFS(明细数据!$L:$L,明细数据!$C:$C,"交易概况",明细数据!$J:$J,"成交金额",明细数据!$K:$K,"本期值",明细数据!$E:$E,">="&$M11,明细数据!$E:$E,"<="&$N11) -> 0 | H11: =SUMIFS(明细数据!$L:$L,明细数据!$C:$C,"交易概况",明细数据!$J:$J,"成交金额",明细数据!$K:$K,"本期值",明细数据!$E:$E,">="&$O11,明细数据!$E:$E,"<="&$P11) -> 0 | I11: =IFERROR(($G11-$K11)/$K11,NA()) -> #N/A | J11: =IFERROR(($G11-$H11)/$H11,NA()) -> #N/A | K11: =SUMIFS(明细数据!$L:$L,明细数据!$C:$C,"交易概况",明细数据!$J:$J,"成交金额",明细数据!$K:$K,"本期值",明细数据!$E:$E,">="&$Q11,明细数据!$E:$E,"<="&$R11) -> 0 | M11: 46289 | N11: 46289 | O11: 46288 | P11: 46288 | Q11: 45924 | R11: 45924 | T11: 本月 | U11: =目标预算!$H$6 -> #N/A | V11: =IFERROR(目标预算!$B$13/目标预算!$B$12,NA()) -> #N/A | W11: =IFERROR(目标预算!$B$12/目标预算!$B$14,NA()) -> #N/A
B12: =SUMIFS(明细数据!$L:$L,明细数据!$C:$C,"流量来源_流量结构分析_场域来源",明细数据!$J:$J,"引入成交金额",明细数据!$K:$K,"本期值",明细数据!$F:$F,$A12) -> 0 | C12: =IFERROR($B12/SUM($B$4:$B$13),NA()) -> #N/A | D12: =IF($B12<=0,"-",RANK($B12,$B$4:$B$13)) -> - | F12: 46290 | G12: =SUMIFS(明细数据!$L:$L,明细数据!$C:$C,"交易概况",明细数据!$J:$J,"成交金额",明细数据!$K:$K,"本期值",明细数据!$E:$E,">="&$M12,明细数据!$E:$E,"<="&$N12) -> 0 | H12: =SUMIFS(明细数据!$L:$L,明细数据!$C:$C,"交易概况",明细数据!$J:$J,"成交金额",明细数据!$K:$K,"本期值",明细数据!$E:$E,">="&$O12,明细数据!$E:$E,"<="&$P12) -> 0 | I12: =IFERROR(($G12-$K12)/$K12,NA()) -> #N/A | J12: =IFERROR(($G12-$H12)/$H12,NA()) -> #N/A | K12: =SUMIFS(明细数据!$L:$L,明细数据!$C:$C,"交易概况",明细数据!$J:$J,"成交金额",明细数据!$K:$K,"本期值",明细数据!$E:$E,">="&$Q12,明细数据!$E:$E,"<="&$R12) -> 0 | M12: 46290 | N12: 46290 | O12: 46289 | P12: 46289 | Q12: 45925 | R12: 45925 | T12: ROI达成 | U12: =IFERROR($V$11/$U$11,NA()) -> #N/A | V12: 费比上限 | W12: =目标预算!$H$7 -> #N/A
B13: =SUMIFS(明细数据!$L:$L,明细数据!$C:$C,"流量来源_流量结构分析_场域来源",明细数据!$J:$J,"引入成交金额",明细数据!$K:$K,"本期值",明细数据!$F:$F,$A13) -> 0 | C13: =IFERROR($B13/SUM($B$4:$B$13),NA()) -> #N/A | D13: =IF($B13<=0,"-",RANK($B13,$B$4:$B$13)) -> - | F13: 46291 | G13: =SUMIFS(明细数据!$L:$L,明细数据!$C:$C,"交易概况",明细数据!$J:$J,"成交金额",明细数据!$K:$K,"本期值",明细数据!$E:$E,">="&$M13,明细数据!$E:$E,"<="&$N13) -> 0 | H13: =SUMIFS(明细数据!$L:$L,明细数据!$C:$C,"交易概况",明细数据!$J:$J,"成交金额",明细数据!$K:$K,"本期值",明细数据!$E:$E,">="&$O13,明细数据!$E:$E,"<="&$P13) -> 0 | I13: =IFERROR(($G13-$K13)/$K13,NA()) -> #N/A | J13: =IFERROR(($G13-$H13)/$H13,NA()) -> #N/A | K13: =SUMIFS(明细数据!$L:$L,明细数据!$C:$C,"交易概况",明细数据!$J:$J,"成交金额",明细数据!$K:$K,"本期值",明细数据!$E:$E,">="&$Q13,明细数据!$E:$E,"<="&$R13) -> 0 | M13: 46291 | N13: 46291 | O13: 46290 | P13: 46290 | Q13: 45926 | R13: 45926
A14: 合计 | B14: =SUM($B$4:$B$13) -> 0 | F14: 46292 | G14: =SUMIFS(明细数据!$L:$L,明细数据!$C:$C,"交易概况",明细数据!$J:$J,"成交金额",明细数据!$K:$K,"本期值",明细数据!$E:$E,">="&$M14,明细数据!$E:$E,"<="&$N14) -> 0 | H14: =SUMIFS(明细数据!$L:$L,明细数据!$C:$C,"交易概况",明细数据!$J:$J,"成交金额",明细数据!$K:$K,"本期值",明细数据!$E:$E,">="&$O14,明细数据!$E:$E,"<="&$P14) -> 0 | I14: =IFERROR(($G14-$K14)/$K14,NA()) -> #N/A | J14: =IFERROR(($G14-$H14)/$H14,NA()) -> #N/A | K14: =SUMIFS(明细数据!$L:$L,明细数据!$C:$C,"交易概况",明细数据!$J:$J,"成交金额",明细数据!$K:$K,"本期值",明细数据!$E:$E,">="&$Q14,明细数据!$E:$E,"<="&$R14) -> 0 | M14: 46292 | N14: 46292 | O14: 46291 | P14: 46291 | Q14: 45927 | R14: 45927
F15: 46293 | G15: =SUMIFS(明细数据!$L:$L,明细数据!$C:$C,"交易概况",明细数据!$J:$J,"成交金额",明细数据!$K:$K,"本期值",明细数据!$E:$E,">="&$M15,明细数据!$E:$E,"<="&$N15) -> 0 | H15: =SUMIFS(明细数据!$L:$L,明细数据!$C:$C,"交易概况",明细数据!$J:$J,"成交金额",明细数据!$K:$K,"本期值",明细数据!$E:$E,">="&$O15,明细数据!$E:$E,"<="&$P15) -> 0 | I15: =IFERROR(($G15-$K15)/$K15,NA()) -> #N/A | J15: =IFERROR(($G15-$H15)/$H15,NA()) -> #N/A | K15: =SUMIFS(明细数据!$L:$L,明细数据!$C:$C,"交易概况",明细数据!$J:$J,"成交金额",明细数据!$K:$K,"本期值",明细数据!$E:$E,">="&$Q15,明细数据!$E:$E,"<="&$R15) -> 0 | M15: 46293 | N15: 46293 | O15: 46292 | P15: 46292 | Q15: 45928 | R15: 45928 | T15: 七、商品-渠道 销售额/件数/下单人数
F16: 46294 | G16: =SUMIFS(明细数据!$L:$L,明细数据!$C:$C,"交易概况",明细数据!$J:$J,"成交金额",明细数据!$K:$K,"本期值",明细数据!$E:$E,">="&$M16,明细数据!$E:$E,"<="&$N16) -> 0 | H16: =SUMIFS(明细数据!$L:$L,明细数据!$C:$C,"交易概况",明细数据!$J:$J,"成交金额",明细数据!$K:$K,"本期值",明细数据!$E:$E,">="&$O16,明细数据!$E:$E,"<="&$P16) -> 0 | I16: =IFERROR(($G16-$K16)/$K16,NA()) -> #N/A | J16: =IFERROR(($G16-$H16)/$H16,NA()) -> #N/A | K16: =SUMIFS(明细数据!$L:$L,明细数据!$C:$C,"交易概况",明细数据!$J:$J,"成交金额",明细数据!$K:$K,"本期值",明细数据!$E:$E,">="&$Q16,明细数据!$E:$E,"<="&$R16) -> 0 | M16: 46294 | N16: 46294 | O16: 46293 | P16: 46293 | Q16: 45929 | R16: 45929 | T16: SPU名称 | U16: 销售额 | V16: 销售件数 | W16: 下单人数 | X16: 占比
F17: 46295 | G17: =SUMIFS(明细数据!$L:$L,明细数据!$C:$C,"交易概况",明细数据!$J:$J,"成交金额",明细数据!$K:$K,"本期值",明细数据!$E:$E,">="&$M17,明细数据!$E:$E,"<="&$N17) -> 0 | H17: =SUMIFS(明细数据!$L:$L,明细数据!$C:$C,"交易概况",明细数据!$J:$J,"成交金额",明细数据!$K:$K,"本期值",明细数据!$E:$E,">="&$O17,明细数据!$E:$E,"<="&$P17) -> 0 | I17: =IFERROR(($G17-$K17)/$K17,NA()) -> #N/A | J17: =IFERROR(($G17-$H17)/$H17,NA()) -> #N/A | K17: =SUMIFS(明细数据!$L:$L,明细数据!$C:$C,"交易概况",明细数据!$J:$J,"成交金额",明细数据!$K:$K,"本期值",明细数据!$E:$E,">="&$Q17,明细数据!$E:$E,"<="&$R17) -> 0 | M17: 46295 | N17: 46295 | O17: 46294 | P17: 46294 | Q17: 45930 | R17: 45930 | U17: =SUMIFS(明细数据!$L:$L,明细数据!$C:$C,"",明细数据!$K:$K,"本期值",明细数据!$H:$H,$T17,明细数据!$J:$J,"成交金额") -> 0 | V17: =SUMIFS(明细数据!$L:$L,明细数据!$C:$C,"",明细数据!$K:$K,"本期值",明细数据!$H:$H,$T17,明细数据!$J:$J,"成交商品件数") -> 0 | W17: =SUMIFS(明细数据!$L:$L,明细数据!$C:$C,"",明细数据!$K:$K,"本期值",明细数据!$H:$H,$T17,明细数据!$J:$J,"成交客户数") -> 0 | X17: =IFERROR($U17/SUM($U$17:$U$28),NA()) -> #N/A
U18: =SUMIFS(明细数据!$L:$L,明细数据!$C:$C,"",明细数据!$K:$K,"本期值",明细数据!$H:$H,$T18,明细数据!$J:$J,"成交金额") -> 0 | V18: =SUMIFS(明细数据!$L:$L,明细数据!$C:$C,"",明细数据!$K:$K,"本期值",明细数据!$H:$H,$T18,明细数据!$J:$J,"成交商品件数") -> 0 | W18: =SUMIFS(明细数据!$L:$L,明细数据!$C:$C,"",明细数据!$K:$K,"本期值",明细数据!$H:$H,$T18,明细数据!$J:$J,"成交客户数") -> 0 | X18: =IFERROR($U18/SUM($U$17:$U$28),NA()) -> #N/A
U19: =SUMIFS(明细数据!$L:$L,明细数据!$C:$C,"",明细数据!$K:$K,"本期值",明细数据!$H:$H,$T19,明细数据!$J:$J,"成交金额") -> 0 | V19: =SUMIFS(明细数据!$L:$L,明细数据!$C:$C,"",明细数据!$K:$K,"本期值",明细数据!$H:$H,$T19,明细数据!$J:$J,"成交商品件数") -> 0 | W19: =SUMIFS(明细数据!$L:$L,明细数据!$C:$C,"",明细数据!$K:$K,"本期值",明细数据!$H:$H,$T19,明细数据!$J:$J,"成交客户数") -> 0 | X19: =IFERROR($U19/SUM($U$17:$U$28),NA()) -> #N/A
F20: 周 | G20: 本期销售额 | H20: 上期销售额 | I20: 同比% | J20: 环比% | K20: 去年同期 | U20: =SUMIFS(明细数据!$L:$L,明细数据!$C:$C,"",明细数据!$K:$K,"本期值",明细数据!$H:$H,$T20,明细数据!$J:$J,"成交金额") -> 0 | V20: =SUMIFS(明细数据!$L:$L,明细数据!$C:$C,"",明细数据!$K:$K,"本期值",明细数据!$H:$H,$T20,明细数据!$J:$J,"成交商品件数") -> 0 | W20: =SUMIFS(明细数据!$L:$L,明细数据!$C:$C,"",明细数据!$K:$K,"本期值",明细数据!$H:$H,$T20,明细数据!$J:$J,"成交客户数") -> 0 | X20: =IFERROR($U20/SUM($U$17:$U$28),NA()) -> #N/A
U21: =SUMIFS(明细数据!$L:$L,明细数据!$C:$C,"",明细数据!$K:$K,"本期值",明细数据!$H:$H,$T21,明细数据!$J:$J,"成交金额") -> 0 | V21: =SUMIFS(明细数据!$L:$L,明细数据!$C:$C,"",明细数据!$K:$K,"本期值",明细数据!$H:$H,$T21,明细数据!$J:$J,"成交商品件数") -> 0 | W21: =SUMIFS(明细数据!$L:$L,明细数据!$C:$C,"",明细数据!$K:$K,"本期值",明细数据!$H:$H,$T21,明细数据!$J:$J,"成交客户数") -> 0 | X21: =IFERROR($U21/SUM($U$17:$U$28),NA()) -> #N/A
U22: =SUMIFS(明细数据!$L:$L,明细数据!$C:$C,"",明细数据!$K:$K,"本期值",明细数据!$H:$H,$T22,明细数据!$J:$J,"成交金额") -> 0 | V22: =SUMIFS(明细数据!$L:$L,明细数据!$C:$C,"",明细数据!$K:$K,"本期值",明细数据!$H:$H,$T22,明细数据!$J:$J,"成交商品件数") -> 0 | W22: =SUMIFS(明细数据!$L:$L,明细数据!$C:$C,"",明细数据!$K:$K,"本期值",明细数据!$H:$H,$T22,明细数据!$J:$J,"成交客户数") -> 0 | X22: =IFERROR($U22/SUM($U$17:$U$28),NA()) -> #N/A
F23: 月 | G23: 本期销售额 | H23: 上期销售额 | I23: 同比% | J23: 环比% | K23: 去年同期 | U23: =SUMIFS(明细数据!$L:$L,明细数据!$C:$C,"",明细数据!$K:$K,"本期值",明细数据!$H:$H,$T23,明细数据!$J:$J,"成交金额") -> 0 | V23: =SUMIFS(明细数据!$L:$L,明细数据!$C:$C,"",明细数据!$K:$K,"本期值",明细数据!$H:$H,$T23,明细数据!$J:$J,"成交商品件数") -> 0 | W23: =SUMIFS(明细数据!$L:$L,明细数据!$C:$C,"",明细数据!$K:$K,"本期值",明细数据!$H:$H,$T23,明细数据!$J:$J,"成交客户数") -> 0 | X23: =IFERROR($U23/SUM($U$17:$U$28),NA()) -> #N/A
F24: 45931 | G24: =SUMIFS(明细数据!$L:$L,明细数据!$C:$C,"交易概况",明细数据!$J:$J,"成交金额",明细数据!$K:$K,"本期值",明细数据!$E:$E,">="&$M24,明细数据!$E:$E,"<="&$N24) -> 0 | H24: =SUMIFS(明细数据!$L:$L,明细数据!$C:$C,"交易概况",明细数据!$J:$J,"成交金额",明细数据!$K:$K,"本期值",明细数据!$E:$E,">="&$O24,明细数据!$E:$E,"<="&$P24) -> 0 | I24: =IFERROR(($G24-$K24)/$K24,NA()) -> #N/A | J24: =IFERROR(($G24-$H24)/$H24,NA()) -> #N/A | K24: =SUMIFS(明细数据!$L:$L,明细数据!$C:$C,"交易概况",明细数据!$J:$J,"成交金额",明细数据!$K:$K,"本期值",明细数据!$E:$E,">="&$Q24,明细数据!$E:$E,"<="&$R24) -> 0 | M24: 45931 | N24: 45961 | O24: 45901 | P24: 45930 | Q24: 45566 | R24: 45596 | U24: =SUMIFS(明细数据!$L:$L,明细数据!$C:$C,"",明细数据!$K:$K,"本期值",明细数据!$H:$H,$T24,明细数据!$J:$J,"成交金额") -> 0 | V24: =SUMIFS(明细数据!$L:$L,明细数据!$C:$C,"",明细数据!$K:$K,"本期值",明细数据!$H:$H,$T24,明细数据!$J:$J,"成交商品件数") -> 0 | W24: =SUMIFS(明细数据!$L:$L,明细数据!$C:$C,"",明细数据!$K:$K,"本期值",明细数据!$H:$H,$T24,明细数据!$J:$J,"成交客户数") -> 0 | X24: =IFERROR($U24/SUM($U$17:$U$28),NA()) -> #N/A
F25: 45962 | G25: =SUMIFS(明细数据!$L:$L,明细数据!$C:$C,"交易概况",明细数据!$J:$J,"成交金额",明细数据!$K:$K,"本期值",明细数据!$E:$E,">="&$M25,明细数据!$E:$E,"<="&$N25) -> 0 | H25: =SUMIFS(明细数据!$L:$L,明细数据!$C:$C,"交易概况",明细数据!$J:$J,"成交金额",明细数据!$K:$K,"本期值",明细数据!$E:$E,">="&$O25,明细数据!$E:$E,"<="&$P25) -> 0 | I25: =IFERROR(($G25-$K25)/$K25,NA()) -> #N/A | J25: =IFERROR(($G25-$H25)/$H25,NA()) -> #N/A | K25: =SUMIFS(明细数据!$L:$L,明细数据!$C:$C,"交易概况",明细数据!$J:$J,"成交金额",明细数据!$K:$K,"本期值",明细数据!$E:$E,">="&$Q25,明细数据!$E:$E,"<="&$R25) -> 0 | M25: 45962 | N25: 45991 | O25: 45931 | P25: 45961 | Q25: 45597 | R25: 45626 | U25: =SUMIFS(明细数据!$L:$L,明细数据!$C:$C,"",明细数据!$K:$K,"本期值",明细数据!$H:$H,$T25,明细数据!$J:$J,"成交金额") -> 0 | V25: =SUMIFS(明细数据!$L:$L,明细数据!$C:$C,"",明细数据!$K:$K,"本期值",明细数据!$H:$H,$T25,明细数据!$J:$J,"成交商品件数") -> 0 | W25: =SUMIFS(明细数据!$L:$L,明细数据!$C:$C,"",明细数据!$K:$K,"本期值",明细数据!$H:$H,$T25,明细数据!$J:$J,"成交客户数") -> 0 | X25: =IFERROR($U25/SUM($U$17:$U$28),NA()) -> #N/A
F26: 45992 | G26: =SUMIFS(明细数据!$L:$L,明细数据!$C:$C,"交易概况",明细数据!$J:$J,"成交金额",明细数据!$K:$K,"本期值",明细数据!$E:$E,">="&$M26,明细数据!$E:$E,"<="&$N26) -> 0 | H26: =SUMIFS(明细数据!$L:$L,明细数据!$C:$C,"交易概况",明细数据!$J:$J,"成交金额",明细数据!$K:$K,"本期值",明细数据!$E:$E,">="&$O26,明细数据!$E:$E,"<="&$P26) -> 0 | I26: =IFERROR(($G26-$K26)/$K26,NA()) -> #N/A | J26: =IFERROR(($G26-$H26)/$H26,NA()) -> #N/A | K26: =SUMIFS(明细数据!$L:$L,明细数据!$C:$C,"交易概况",明细数据!$J:$J,"成交金额",明细数据!$K:$K,"本期值",明细数据!$E:$E,">="&$Q26,明细数据!$E:$E,"<="&$R26) -> 0 | M26: 45992 | N26: 46022 | O26: 45962 | P26: 45991 | Q26: 45627 | R26: 45657 | U26: =SUMIFS(明细数据!$L:$L,明细数据!$C:$C,"",明细数据!$K:$K,"本期值",明细数据!$H:$H,$T26,明细数据!$J:$J,"成交金额") -> 0 | V26: =SUMIFS(明细数据!$L:$L,明细数据!$C:$C,"",明细数据!$K:$K,"本期值",明细数据!$H:$H,$T26,明细数据!$J:$J,"成交商品件数") -> 0 | W26: =SUMIFS(明细数据!$L:$L,明细数据!$C:$C,"",明细数据!$K:$K,"本期值",明细数据!$H:$H,$T26,明细数据!$J:$J,"成交客户数") -> 0 | X26: =IFERROR($U26/SUM($U$17:$U$28),NA()) -> #N/A
F27: 46023 | G27: =SUMIFS(明细数据!$L:$L,明细数据!$C:$C,"交易概况",明细数据!$J:$J,"成交金额",明细数据!$K:$K,"本期值",明细数据!$E:$E,">="&$M27,明细数据!$E:$E,"<="&$N27) -> 0 | H27: =SUMIFS(明细数据!$L:$L,明细数据!$C:$C,"交易概况",明细数据!$J:$J,"成交金额",明细数据!$K:$K,"本期值",明细数据!$E:$E,">="&$O27,明细数据!$E:$E,"<="&$P27) -> 0 | I27: =IFERROR(($G27-$K27)/$K27,NA()) -> #N/A | J27: =IFERROR(($G27-$H27)/$H27,NA()) -> #N/A | K27: =SUMIFS(明细数据!$L:$L,明细数据!$C:$C,"交易概况",明细数据!$J:$J,"成交金额",明细数据!$K:$K,"本期值",明细数据!$E:$E,">="&$Q27,明细数据!$E:$E,"<="&$R27) -> 0 | M27: 46023 | N27: 46053 | O27: 45992 | P27: 46022 | Q27: 45658 | R27: 45688 | U27: =SUMIFS(明细数据!$L:$L,明细数据!$C:$C,"",明细数据!$K:$K,"本期值",明细数据!$H:$H,$T27,明细数据!$J:$J,"成交金额") -> 0 | V27: =SUMIFS(明细数据!$L:$L,明细数据!$C:$C,"",明细数据!$K:$K,"本期值",明细数据!$H:$H,$T27,明细数据!$J:$J,"成交商品件数") -> 0 | W27: =SUMIFS(明细数据!$L:$L,明细数据!$C:$C,"",明细数据!$K:$K,"本期值",明细数据!$H:$H,$T27,明细数据!$J:$J,"成交客户数") -> 0 | X27: =IFERROR($U27/SUM($U$17:$U$28),NA()) -> #N/A
F28: 46054 | G28: =SUMIFS(明细数据!$L:$L,明细数据!$C:$C,"交易概况",明细数据!$J:$J,"成交金额",明细数据!$K:$K,"本期值",明细数据!$E:$E,">="&$M28,明细数据!$E:$E,"<="&$N28) -> 0 | H28: =SUMIFS(明细数据!$L:$L,明细数据!$C:$C,"交易概况",明细数据!$J:$J,"成交金额",明细数据!$K:$K,"本期值",明细数据!$E:$E,">="&$O28,明细数据!$E:$E,"<="&$P28) -> 0 | I28: =IFERROR(($G28-$K28)/$K28,NA()) -> #N/A | J28: =IFERROR(($G28-$H28)/$H28,NA()) -> #N/A | K28: =SUMIFS(明细数据!$L:$L,明细数据!$C:$C,"交易概况",明细数据!$J:$J,"成交金额",明细数据!$K:$K,"本期值",明细数据!$E:$E,">="&$Q28,明细数据!$E:$E,"<="&$R28) -> 0 | M28: 46054 | N28: 46081 | O28: 46023 | P28: 46053 | Q28: 45689 | R28: 45716 | U28: =SUMIFS(明细数据!$L:$L,明细数据!$C:$C,"",明细数据!$K:$K,"本期值",明细数据!$H:$H,$T28,明细数据!$J:$J,"成交金额") -> 0 | V28: =SUMIFS(明细数据!$L:$L,明细数据!$C:$C,"",明细数据!$K:$K,"本期值",明细数据!$H:$H,$T28,明细数据!$J:$J,"成交商品件数") -> 0 | W28: =SUMIFS(明细数据!$L:$L,明细数据!$C:$C,"",明细数据!$K:$K,"本期值",明细数据!$H:$H,$T28,明细数据!$J:$J,"成交客户数") -> 0 | X28: =IFERROR($U28/SUM($U$17:$U$28),NA()) -> #N/A
F29: 46082 | G29: =SUMIFS(明细数据!$L:$L,明细数据!$C:$C,"交易概况",明细数据!$J:$J,"成交金额",明细数据!$K:$K,"本期值",明细数据!$E:$E,">="&$M29,明细数据!$E:$E,"<="&$N29) -> 0 | H29: =SUMIFS(明细数据!$L:$L,明细数据!$C:$C,"交易概况",明细数据!$J:$J,"成交金额",明细数据!$K:$K,"本期值",明细数据!$E:$E,">="&$O29,明细数据!$E:$E,"<="&$P29) -> 0 | I29: =IFERROR(($G29-$K29)/$K29,NA()) -> #N/A | J29: =IFERROR(($G29-$H29)/$H29,NA()) -> #N/A | K29: =SUMIFS(明细数据!$L:$L,明细数据!$C:$C,"交易概况",明细数据!$J:$J,"成交金额",明细数据!$K:$K,"本期值",明细数据!$E:$E,">="&$Q29,明细数据!$E:$E,"<="&$R29) -> 0 | M29: 46082 | N29: 46112 | O29: 46054 | P29: 46081 | Q29: 45717 | R29: 45747
F30: 46113 | G30: =SUMIFS(明细数据!$L:$L,明细数据!$C:$C,"交易概况",明细数据!$J:$J,"成交金额",明细数据!$K:$K,"本期值",明细数据!$E:$E,">="&$M30,明细数据!$E:$E,"<="&$N30) -> 0 | H30: =SUMIFS(明细数据!$L:$L,明细数据!$C:$C,"交易概况",明细数据!$J:$J,"成交金额",明细数据!$K:$K,"本期值",明细数据!$E:$E,">="&$O30,明细数据!$E:$E,"<="&$P30) -> 0 | I30: =IFERROR(($G30-$K30)/$K30,NA()) -> #N/A | J30: =IFERROR(($G30-$H30)/$H30,NA()) -> #N/A | K30: =SUMIFS(明细数据!$L:$L,明细数据!$C:$C,"交易概况",明细数据!$J:$J,"成交金额",明细数据!$K:$K,"本期值",明细数据!$E:$E,">="&$Q30,明细数据!$E:$E,"<="&$R30) -> 0 | M30: 46113 | N30: 46142 | O30: 46082 | P30: 46112 | Q30: 45748 | R30: 45777
F31: 46143 | G31: =SUMIFS(明细数据!$L:$L,明细数据!$C:$C,"交易概况",明细数据!$J:$J,"成交金额",明细数据!$K:$K,"本期值",明细数据!$E:$E,">="&$M31,明细数据!$E:$E,"<="&$N31) -> 0 | H31: =SUMIFS(明细数据!$L:$L,明细数据!$C:$C,"交易概况",明细数据!$J:$J,"成交金额",明细数据!$K:$K,"本期值",明细数据!$E:$E,">="&$O31,明细数据!$E:$E,"<="&$P31) -> 0 | I31: =IFERROR(($G31-$K31)/$K31,NA()) -> #N/A | J31: =IFERROR(($G31-$H31)/$H31,NA()) -> #N/A | K31: =SUMIFS(明细数据!$L:$L,明细数据!$C:$C,"交易概况",明细数据!$J:$J,"成交金额",明细数据!$K:$K,"本期值",明细数据!$E:$E,">="&$Q31,明细数据!$E:$E,"<="&$R31) -> 0 | M31: 46143 | N31: 46173 | O31: 46113 | P31: 46142 | Q31: 45778 | R31: 45808
F32: 46174 | G32: =SUMIFS(明细数据!$L:$L,明细数据!$C:$C,"交易概况",明细数据!$J:$J,"成交金额",明细数据!$K:$K,"本期值",明细数据!$E:$E,">="&$M32,明细数据!$E:$E,"<="&$N32) -> 0 | H32: =SUMIFS(明细数据!$L:$L,明细数据!$C:$C,"交易概况",明细数据!$J:$J,"成交金额",明细数据!$K:$K,"本期值",明细数据!$E:$E,">="&$O32,明细数据!$E:$E,"<="&$P32) -> 0 | I32: =IFERROR(($G32-$K32)/$K32,NA()) -> #N/A | J32: =IFERROR(($G32-$H32)/$H32,NA()) -> #N/A | K32: =SUMIFS(明细数据!$L:$L,明细数据!$C:$C,"交易概况",明细数据!$J:$J,"成交金额",明细数据!$K:$K,"本期值",明细数据!$E:$E,">="&$Q32,明细数据!$E:$E,"<="&$R32) -> 0 | M32: 46174 | N32: 46203 | O32: 46143 | P32: 46173 | Q32: 45809 | R32: 45838
F33: 46204 | G33: =SUMIFS(明细数据!$L:$L,明细数据!$C:$C,"交易概况",明细数据!$J:$J,"成交金额",明细数据!$K:$K,"本期值",明细数据!$E:$E,">="&$M33,明细数据!$E:$E,"<="&$N33) -> 0 | H33: =SUMIFS(明细数据!$L:$L,明细数据!$C:$C,"交易概况",明细数据!$J:$J,"成交金额",明细数据!$K:$K,"本期值",明细数据!$E:$E,">="&$O33,明细数据!$E:$E,"<="&$P33) -> 0 | I33: =IFERROR(($G33-$K33)/$K33,NA()) -> #N/A | J33: =IFERROR(($G33-$H33)/$H33,NA()) -> #N/A | K33: =SUMIFS(明细数据!$L:$L,明细数据!$C:$C,"交易概况",明细数据!$J:$J,"成交金额",明细数据!$K:$K,"本期值",明细数据!$E:$E,">="&$Q33,明细数据!$E:$E,"<="&$R33) -> 0 | M33: 46204 | N33: 46234 | O33: 46174 | P33: 46203 | Q33: 45839 | R33: 45869
F34: 46235 | G34: =SUMIFS(明细数据!$L:$L,明细数据!$C:$C,"交易概况",明细数据!$J:$J,"成交金额",明细数据!$K:$K,"本期值",明细数据!$E:$E,">="&$M34,明细数据!$E:$E,"<="&$N34) -> 0 | H34: =SUMIFS(明细数据!$L:$L,明细数据!$C:$C,"交易概况",明细数据!$J:$J,"成交金额",明细数据!$K:$K,"本期值",明细数据!$E:$E,">="&$O34,明细数据!$E:$E,"<="&$P34) -> 0 | I34: =IFERROR(($G34-$K34)/$K34,NA()) -> #N/A | J34: =IFERROR(($G34-$H34)/$H34,NA()) -> #N/A | K34: =SUMIFS(明细数据!$L:$L,明细数据!$C:$C,"交易概况",明细数据!$J:$J,"成交金额",明细数据!$K:$K,"本期值",明细数据!$E:$E,">="&$Q34,明细数据!$E:$E,"<="&$R34) -> 0 | M34: 46235 | N34: 46265 | O34: 46204 | P34: 46234 | Q34: 45870 | R34: 45900
F35: 46266 | G35: =SUMIFS(明细数据!$L:$L,明细数据!$C:$C,"交易概况",明细数据!$J:$J,"成交金额",明细数据!$K:$K,"本期值",明细数据!$E:$E,">="&$M35,明细数据!$E:$E,"<="&$N35) -> 0 | H35: =SUMIFS(明细数据!$L:$L,明细数据!$C:$C,"交易概况",明细数据!$J:$J,"成交金额",明细数据!$K:$K,"本期值",明细数据!$E:$E,">="&$O35,明细数据!$E:$E,"<="&$P35) -> 0 | I35: =IFERROR(($G35-$K35)/$K35,NA()) -> #N/A | J35: =IFERROR(($G35-$H35)/$H35,NA()) -> #N/A | K35: =SUMIFS(明细数据!$L:$L,明细数据!$C:$C,"交易概况",明细数据!$J:$J,"成交金额",明细数据!$K:$K,"本期值",明细数据!$E:$E,">="&$Q35,明细数据!$E:$E,"<="&$R35) -> 0 | M35: 46266 | N35: 46295 | O35: 46235 | P35: 46265 | Q35: 45901 | R35: 45930
F38: 年 | G38: 本期销售额 | H38: 上期销售额 | I38: 同比% | J38: 环比% | K38: 去年同期
F39: 2025 年 | G39: =SUMIFS(明细数据!$L:$L,明细数据!$C:$C,"交易概况",明细数据!$J:$J,"成交金额",明细数据!$K:$K,"本期值",明细数据!$E:$E,">="&$M39,明细数据!$E:$E,"<="&$N39) -> 0 | H39: =SUMIFS(明细数据!$L:$L,明细数据!$C:$C,"交易概况",明细数据!$J:$J,"成交金额",明细数据!$K:$K,"本期值",明细数据!$E:$E,">="&$O39,明细数据!$E:$E,"<="&$P39) -> 0 | I39: =IFERROR(($G39-$K39)/$K39,NA()) -> #N/A | J39: =IFERROR(($G39-$H39)/$H39,NA()) -> #N/A | K39: =SUMIFS(明细数据!$L:$L,明细数据!$C:$C,"交易概况",明细数据!$J:$J,"成交金额",明细数据!$K:$K,"本期值",明细数据!$E:$E,">="&$Q39,明细数据!$E:$E,"<="&$R39) -> 0 | M39: 45658 | N39: 46022 | O39: 45292 | P39: 45657 | Q39: 44927 | R39: 45291
F40: 2026 年 | G40: =SUMIFS(明细数据!$L:$L,明细数据!$C:$C,"交易概况",明细数据!$J:$J,"成交金额",明细数据!$K:$K,"本期值",明细数据!$E:$E,">="&$M40,明细数据!$E:$E,"<="&$N40) -> 0 | H40: =SUMIFS(明细数据!$L:$L,明细数据!$C:$C,"交易概况",明细数据!$J:$J,"成交金额",明细数据!$K:$K,"本期值",明细数据!$E:$E,">="&$O40,明细数据!$E:$E,"<="&$P40) -> 0 | I40: =IFERROR(($G40-$K40)/$K40,NA()) -> #N/A | J40: =IFERROR(($G40-$H40)/$H40,NA()) -> #N/A | K40: =SUMIFS(明细数据!$L:$L,明细数据!$C:$C,"交易概况",明细数据!$J:$J,"成交金额",明细数据!$K:$K,"本期值",明细数据!$E:$E,">="&$Q40,明细数据!$E:$E,"<="&$R40) -> 0 | M40: 46023 | N40: 46387 | O40: 45658 | P40: 46022 | Q40: 45292 | R40: 45657

Sheet 目标预算
A1: 目标与预算输入表（黄色单元格人工填写；有目标文件时脚本自动预填）
G2: 当前考核月份(可改) | H2: 46266
A3: 月份 | B3: 月度目标 | C3: 广告预算 | D3: ROI目标 | E3: 费比上限 | G3: 月度目标 | H3: =IFERROR(VLOOKUP($H$2,$A$4:$E$18,2,FALSE),NA()) -> #N/A
A4: 45839 | G4: 年度累计目标 | H4: =IFERROR(SUMIFS($B$4:$B$18,$A$4:$A$18,"<="&$H$2),NA()) -> 0
A5: 45870 | G5: 当月广告预算 | H5: =IFERROR(VLOOKUP($H$2,$A$4:$E$18,3,FALSE),NA()) -> #N/A
A6: 45901 | G6: ROI目标 | H6: =IFERROR(VLOOKUP($H$2,$A$4:$E$18,4,FALSE),NA()) -> #N/A
A7: 45931 | G7: 费比上限 | H7: =IFERROR(VLOOKUP($H$2,$A$4:$E$18,5,FALSE),NA()) -> #N/A
A8: 45962
A9: 45992
A10: 六、广告预算使用率 与 全月使用进度（表格）
A11: 指标 | B11: 数值 | C11: 口径说明
A12: 当月广告花费 | B12: =SUMIFS(明细数据!$L:$L,明细数据!$C:$C,"全站营销_推广管理_单品推广",明细数据!$J:$J,"花费",明细数据!$K:$K,"本期值",明细数据!$E:$E,">="&目标预算!$H$2,明细数据!$E:$E,"<="&目标预算!$H$2+32-DAY(目标预算!$H$2)) -> 0 | C12: 推广报表花费合计
A13: 当月广告成交额 | B13: =SUMIFS(明细数据!$L:$L,明细数据!$C:$C,"全站营销_推广管理_单品推广",明细数据!$J:$J,"全站交易额",明细数据!$K:$K,"本期值",明细数据!$E:$E,">="&目标预算!$H$2,明细数据!$E:$E,"<="&目标预算!$H$2+32-DAY(目标预算!$H$2)) -> 0 | C13: 全站交易额合计
A14: 当月销售额 | B14: =SUMIFS(明细数据!$L:$L,明细数据!$C:$C,"交易概况",明细数据!$J:$J,"成交金额",明细数据!$K:$K,"本期值",明细数据!$E:$E,">="&目标预算!$H$2,明细数据!$E:$E,"<="&目标预算!$H$2+32-DAY(目标预算!$H$2)) -> 0 | C14: 成交金额合计（费比分母）
A15: 月度广告预算 | B15: =$H$5 -> #N/A | C15: 取自本表 H5
A16: 当前使用率 | B16: =IFERROR($B$12/$B$15,NA()) -> #N/A | C16: 已花费 / 预算
A17: 时间进度 | B17: =IFERROR(DAY(目标预算!$H$2+32-DAY(目标预算!$H$2))/DAY(EOMONTH(目标预算!$H$2,0)),NA()) -> 0.066666667 | C17: 已过天数 / 当月总天数
A18: 全月使用进度 | B18: =IFERROR($B$16-$B$17,NA()) -> #N/A | C18: 使用率 - 时间进度；正数=花钱快于走日历
A19: 实际ROI | B19: =IFERROR($B$13/$B$12,NA()) -> #N/A | C19: 广告成交额 / 花费
A20: ROI目标 | B20: =$H$6 -> #N/A | C20: 取自本表 H6
A21: ROI达成 | B21: =IFERROR($B$19/$B$20,NA()) -> #N/A | C21: 实际ROI / ROI目标
A22: 花费比例(费比) | B22: =IFERROR($B$12/$B$14,NA()) -> #N/A | C22: 花费 / 销售额
A23: 费比上限 | B23: =$H$7 -> #N/A | C23: 取自本表 H7
A24: 预算预警 | B24: =IF($B$16>$B$17+0.05,"超前花钱",IF($B$16<$B$17-0.15,"投放不足","进度正常")) -> #N/A | C24: 使用率对比时间进度的阈值判断

Sheet Summary
A1: 京东 商智数据透析表
A3: 平台 | B3: 京东
A4: 店铺/品牌(自动识别) | B4: 11623441、未标注、小巴依-奔羊羊
A5: 文件名店铺标识 | B5: 奔养养
A6: 出表日期 | B6: 46295.75
A7: 输出文件 | B7: 京东_奔养养_26-09-30.xlsx
A8: 源文件数 | B8: 8
A9: 报表类型数 | B9: 8
A10: 解析列总数 | B10: 391
A11: 去重度量指标数 | B11: 120
A12: 去重维度数 | B12: 19
A13: 源数据行数 | B13: 0
A14: 时间趋势行数 | B14: 3
A15: 透视表模式 | B15: 原生透视表（可刷新）
A17: 注意：全部源文件当前只有表头、没有数据行（Excel UsedRange 与 xlsx 内部 dimension 双重核验）。
A18: 本次交付 =「元数据透析 + 待填充结构」。把带数据行的导出放回本目录后重跑脚本，各 sheet 自动出数。
A20: 命名规则与逐文件解析结果见「文件清单」sheet；字段语义见「指标总览」sheet。

Sheet 文件清单
A1: 源文件 | B1: 店铺/品牌 | C1: 报表类型 | D1: 下载方式 | E1: 时间粒度 | F1: 对比口径 | G1: 统计起 | H1: 统计止 | I1: 列数 | J1: 数据行数
A2: 11623441_交易概况_包括对比时间_离线_分天下载_2026-09-28_2026-09-28.xlsx | B2: 11623441 | C2: 交易概况 | D2: 离线 | E2: 分天 | F2: 包括对比时间 | G2: 46293 | H2: 46293 | I2: 130 | J2: 0
A3: 11623441_流量概况-核心指标_分天下载_2026-09-28_2026-09-28.xlsx | B3: 11623441 | C3: 流量概况-核心指标 | D3: 未标注 | E3: 分天 | F3: 无 | G3: 46293 | H3: 46293 | I3: 58 | J3: 0
A4: 11623441_流量来源_流量结构分析_场域来源_实时_汇总下载_2026-09-29_00_00_00_2026-09-29_10_00_41.xlsx | B4: 11623441 | C4: 流量来源_流量结构分析_场域来源 | D4: 实时 | E4: 汇总 | F4: 无 | G4: 46294 | H4: 46294.417 | I4: 35 | J4: 0
A5: 11623441_商品概况_离线_分天下载_2026-09-28_2026-09-28.xlsx | B5: 11623441 | C5: 商品概况 | D5: 离线 | E5: 分天 | F5: 无 | G5: 46293 | H5: 46293 | I5: 61 | J5: 0
A6: 11623441_商品明细_实时_汇总下载_2026-09-29_00_00_00_2026-09-29_10_00_21.xlsx | B6: 11623441 | C6: 商品明细 | D6: 实时 | E6: 汇总 | F6: 无 | G6: 46294 | H6: 46294.417 | I6: 27 | J6: 0
A7: 小巴依-奔羊羊_报表中心_计划_30天_点击_不含赠品_成交订单_20260923_20260929.csv | B7: 小巴依-奔羊羊 | C7: 报表中心_计划_30天_点击_不含赠品_成交订单 | D7: 未标注 | E7: 未标注 | F7: 无 | G7: 46288 | H7: 46294 | I7: 37 | J7: 0
A8: 小巴依-奔羊羊_全站营销_推广管理_单品推广_20260923_20260929.csv | B8: 小巴依-奔羊羊 | C8: 全站营销_推广管理_单品推广 | D8: 未标注 | E8: 未标注 | F8: 无 | G8: 46288 | H8: 46294 | I8: 16 | J8: 0
A9: 用户洞察-数据概览-2026.09.28-同比.xlsx | B9: - | C9: 用户洞察-数据概览 | D9: 未标注 | E9: 未标注 | F9: 同比 | G9: 46293 | H9: 46293 | I9: 27 | J9: 1

Sheet 明细数据
A1: 平台 | B1: 店铺/品牌 | C1: 报表类型 | D1: 时间粒度 | E1: 统计日期 | F1: 渠道 | G1: SPU | H1: SPU名称 | I1: 维度组合 | J1: 基础指标名 | K1: 列角色 | L1: 数值 | M1: 来源文件

Sheet 透视表
A1: 活透视表：行=报表类型，列=列角色，值=列数计数。数据行落地后可把值字段换成「明细数据」的数值求和。
B4: 列标签
B5: 本期值 | D5: 对比日 | F5: 较对比日 | H5: 同比 | J5: 维度 | L5: 列数汇总 | M5: 度量列数汇总
A6: 行标签 | B6: 列数 | C6: 度量列数 | D6: 列数 | E6: 度量列数 | F6: 列数 | G6: 度量列数 | H6: 列数 | I6: 度量列数 | J6: 列数 | K6: 度量列数
A7: 报表中心_计划_30天_点击_不含赠品_成交订单 | B7: 37 | C7: 37 | L7: 37 | M7: 37
A8: 交易概况 | B8: 43 | C8: 43 | D8: 43 | E8: 43 | F8: 43 | G8: 43 | J8: 1 | K8: 1 | L8: 130 | M8: 130
A9: 流量概况-核心指标 | B9: 19 | C9: 19 | D9: 19 | E9: 19 | F9: 19 | G9: 19 | J9: 1 | K9: 1 | L9: 58 | M9: 58
A10: 流量来源_流量结构分析_场域来源 | B10: 10 | C10: 10 | D10: 10 | E10: 10 | F10: 10 | G10: 10 | J10: 5 | K10: 5 | L10: 35 | M10: 35
A11: 全站营销_推广管理_单品推广 | B11: 9 | C11: 9 | J11: 7 | K11: 7 | L11: 16 | M11: 16
A12: 商品概况 | B12: 20 | C12: 20 | D12: 20 | E12: 20 | F12: 20 | G12: 20 | J12: 1 | K12: 1 | L12: 61 | M12: 61
A13: 商品明细 | B13: 20 | C13: 20 | J13: 7 | K13: 7 | L13: 27 | M13: 27
A14: 用户洞察-数据概览 | B14: 13 | C14: 13 | H14: 13 | I14: 13 | J14: 1 | K14: 1 | L14: 27 | M14: 27
A15: 总计 | B15: 171 | C15: 171 | D15: 92 | E15: 92 | F15: 92 | G15: 92 | H15: 13 | I15: 13 | J15: 23 | K15: 23 | L15: 391 | M15: 391

Sheet 时间趋势
A1: 日期 | B1: 粒度 | C1: UV价值 | D1: 成交单量 | E1: 成交金额 | F1: 成交客户数 | G1: 成交商品件数 | H1: 成交转化率 | I1: 店铺访客数 | J1: 店铺浏览量 | K1: 加购客户数 | L1: 加购商品件数 | M1: 件单价 | N1: 客单价 | O1: 商品访客数 | P1: 商品浏览量 | Q1: 退款金额 | R1: 下单金额 | S1: UV价值 日环比 | T1: 成交单量 日环比 | U1: 成交金额 日环比 | V1: 成交客户数 日环比 | W1: 成交商品件数 日环比 | X1: 成交转化率 日环比 | Y1: 店铺访客数 日环比 | Z1: 店铺浏览量 日环比 | AA1: 加购客户数 日环比 | AB1: 加购商品件数 日环比 | AC1: 件单价 日环比 | AD1: 客单价 日环比 | AE1: 商品访客数 日环比 | AF1: 商品浏览量 日环比 | AG1: 退款金额 日环比 | AH1: 下单金额 日环比
A2: 46288 | B2: 日
A3: 46293 | B3: 日
A4: 46294 | B4: 日

Sheet 渠道维度
A1: 日期 | B1: 一级渠道 | C1: 二级渠道 | D1: 三级渠道 | E1: 四级渠道 | F1: 引入商详访客数 | G1: 引入商详浏览量 | H1: UV价值 | I1: 客单价 | J1: 引入成交客户数 | K1: 引入成交金额 | L1: 引入成交商品件数 | M1: 引入成交单量 | N1: 访客-成交转化率 | O1: 浏览-成交转化率

Sheet 商品维度
A1: 日期 | B1: SPU | C1: SPU名称 | D1: 一级类目 | E1: 二级类目 | F1: 三级类目 | G1: 货号 | H1: 成交金额 | I1: 成交商品件数 | J1: 成交单量 | K1: 成交客户数 | L1: 成交转化率 | M1: 客单价 | N1: 件单价 | O1: UV价值 | P1: 商品浏览量 | Q1: 商品访客数 | R1: 商品人均浏览量 | S1: 加购商品件数 | T1: 加购客户数 | U1: 加购商品件数（正向） | V1: 加购商品件数（负向） | W1: 加购转化率 | X1: 加购金额 | Y1: 取消订单金额 | Z1: 取消订单商品件数 | AA1: 取消订单单量
